pyvertools/__init__.py
pyvertools/converter.py
pyvertools/detector.py
pyvertools-0.1.0.data/scripts/f23
pyvertools-0.1.0.data/scripts/is23
pyvertools-0.1.0.dist-info/licenses/LICENSE
pyvertools-0.1.0.dist-info/METADATA
pyvertools-0.1.0.dist-info/WHEEL
pyvertools-0.1.0.dist-info/top_level.txt
pyvertools-0.1.0.dist-info/RECORD
