Metadata-Version: 2.4
Name: pyvertools
Version: 0.1.0
Summary: Tools to detect Python version and convert Python 2 to 3
Author: Your Name
Classifier: Programming Language :: Python :: 3
Classifier: Programming Language :: Python :: 2
Classifier: License :: OSI Approved :: MIT License
Classifier: Operating System :: OS Independent
License-File: LICENSE
Dynamic: author
Dynamic: classifier
Dynamic: license-file
Dynamic: summary
